orb_analysis/__init__.py
orb_analysis/custom_types.py
orb_analysis/log_messages.py
orb_analysis/main.py
orb_analysis/analyzer/__init__.py
orb_analysis/analyzer/calc_analyzer.py
orb_analysis/analyzer/calc_info.py
orb_analysis/complex/__init__.py
orb_analysis/complex/complex.py
orb_analysis/complex/complex_data.py
orb_analysis/fragment/__init__.py
orb_analysis/fragment/fragment.py
orb_analysis/fragment/fragmentdata.py
orb_analysis/orbital/__init__.py
orb_analysis/orbital/orbital.py
orb_visualization/__init__.py
orb_visualization/densf_presets.py
orb_visualization/plotter.py
orb_analysis-0.1.2.dist-info/LICENSE
orb_analysis-0.1.2.dist-info/METADATA
orb_analysis-0.1.2.dist-info/WHEEL
orb_analysis-0.1.2.dist-info/entry_points.txt
orb_analysis-0.1.2.dist-info/top_level.txt
orb_analysis-0.1.2.dist-info/RECORD
