Metadata-Version: 2.1
Name: orb_analysis
Version: 0.1.2
Summary: the package can be used for analysing fragment calculations with the AMS software package
Author: Siebe Lekanne Deprez
Author-email: s.j.lekanne.deprez@vu.nl
License: MIT
Classifier: Programming Language :: Python :: 3.10
Classifier: License :: OSI Approved :: MIT License
Classifier: Operating System :: OS Independent
License-File: LICENSE
Requires-Dist: numpy >=1.20.0
Requires-Dist: gitpython >=3.1.24
Requires-Dist: plams
Requires-Dist: attrs >=21.2.0
Requires-Dist: pandas >=1.4.0
Requires-Dist: tabulate >=0.8.9
Requires-Dist: importlib-metadata ; python_version > "3.10"
Provides-Extra: dev
Requires-Dist: pytest ; extra == 'dev'
Requires-Dist: sphinx ; extra == 'dev'
